imem.v
module imem(
    input [31:0] addr,
    output [31:0] instr
);

reg [31:0] memory [0:255];

initial begin
    $readmemh("prog.hex", memory);
end

assign instr = memory[addr >> 2];

endmodule

pc.v
module pc(
    input clk,
    input reset,
    output reg [31:0] pc
);

always @(posedge clk) begin
    if(reset)
        pc <= 0;
    else
        pc <= pc + 4;
end

endmodule

cpu.v
module cpu(
    input clk,
    input reset
);

wire [31:0] pc;
wire [31:0] instr;

pc pc0(clk, reset, pc);
imem im0(pc, instr);

endmodule

test_bench.v
`timescale 1ns/1ps

module testbench;

reg clk;
reg reset;

cpu uut(
    .clk(clk),
    .reset(reset)
);

initial begin
    clk = 0;
    forever #5 clk = ~clk;
end

initial begin
    reset = 1;
    #10;
    reset = 0;
end

initial begin
    $dumpfile("wave.vcd");
    $dumpvars(0, testbench);
end

initial begin
    #200 $finish;
end

endmodule

wave.vcd
$date
	Tue Mar 31 23:30:08 2026
$end
$version
	Icarus Verilog
$end
$timescale
	1ps
$end
$scope module testbench $end
$var reg 1 ! clk $end
$var reg 1 " reset $end
$scope module uut $end
$var wire 1 ! clk $end
$var wire 1 " reset $end
$var wire 32 # pc [31:0] $end
$var wire 32 $ instr [31:0] $end
$scope module im0 $end
$var wire 32 % instr [31:0] $end
$var wire 32 & addr [31:0] $end
$upscope $end
$scope module pc0 $end
$var wire 1 ! clk $end
$var wire 1 " reset $end
$var reg 32 ' pc [31:0] $end
$upscope $end
$upscope $end
$upscope $end
$enddefinitions $end
$comment Show the parameter values. $end
$dumpall
$end
#0
$dumpvars
bx '
bx &
bx %
bx $
bx #
1"
0!
$end
#5000
b10100000000000010010011 $
b10100000000000010010011 %
b0 #
b0 &
b0 '
1!
#10000
0!
0"
#15000
b100000010000000100011 $
b100000010000000100011 %
b100 #
b100 &
b100 '
1!
#20000
0!
#25000
b10000100000011 $
b10000100000011 %
b1000 #
b1000 &
b1000 '
1!
#30000
0!
#35000
bx $
bx %
b1100 #
b1100 &
b1100 '
1!
#40000
0!
#45000
b10000 #
b10000 &
b10000 '
1!
#50000
0!
#55000
b10100 #
b10100 &
b10100 '
1!
#60000
0!
#65000
b11000 #
b11000 &
b11000 '
1!
#70000
0!
#75000
b11100 #
b11100 &
b11100 '
1!
#80000
0!
#85000
b100000 #
b100000 &
b100000 '
1!
#90000
0!
#95000
b100100 #
b100100 &
b100100 '
1!
#100000
0!
#105000
b101000 #
b101000 &
b101000 '
1!
#110000
0!
#115000
b101100 #
b101100 &
b101100 '
1!
#120000
0!
#125000
b110000 #
b110000 &
b110000 '
1!
#130000
0!
#135000
b110100 #
b110100 &
b110100 '
1!
#140000
0!
#145000
b111000 #
b111000 &
b111000 '
1!
#150000
0!
#155000
b111100 #
b111100 &
b111100 '
1!
#160000
0!
#165000
b1000000 #
b1000000 &
b1000000 '
1!
#170000
0!
#175000
b1000100 #
b1000100 &
b1000100 '
1!
#180000
0!
#185000
b1001000 #
b1001000 &
b1001000 '
1!
#190000
0!
#195000
b1001100 #
b1001100 &
b1001100 '
1!
